Workbook

Sheet Cover
A1: Cover
A2: Created By: Elizabeth Garcia
A3: Start Date: 6/29/2026
A4: End Date: 7/5/2026
A5: Description: This DCF Model uses 5 years of Starbucks' Historical data to evaluate the value of Starbucks Corporation today based on the cash Starbucks is expected to make in the future.

Sheet Historical Financials 
A1: Starbucks Corporation
A2: Historical Financials
A3: ($ in millions)
A5: Metric | C5: 2021 | D5: 2022 | E5: 2023 | F5: 2024 | G5: 2025
A7: Total Net Revenue | C7: 29060.6 | D7: 32250.3 | E7: 35975.6 | F7: 36176.2 | G7: 37184.4
A8: Operating Income | C8: 4872.1 | D8: 4617.8 | E8: 5870.8 | F8: 5408.8 | G8: 2936.6
A9: Earnings Before Income Taxes | C9: 5356.9 | D9: 4231.9 | E9: 5401.9 | F9: 4969.6 | G9: 2507.3
A10: Income Tax Expense | C10: 1156.6 | D10: 948.5 | E10: 1277.2 | F10: 1207.3 | G10: 650.6
A11: Net Income | C11: 4199.3 | D11: 3281.6 | E11: 4124.5 | F11: 3760.9 | G11: 1856.4
A12: Depreciation & Amoritization | C12: 1524.1 | D12: 1529.4 | E12: 1450.3 | F12: 1592.4 | G12: 1771.5
A13: Capital Expenditures(CapEx) | C13: 1470 | D13: 1841.3 | E13: 2333.6 | F13: 2777.5 | G13: 2305.5
A14: Cash and Cash Equivalents | C14: 6455.7 | D14: 2818.4 | E14: 3551.5 | F14: 3286.2 | G14: 3219.8
A15: Accounts Receivable | C15: 940 | D15: 1175.5 | E15: 1184.1 | F15: 1213.8 | G15: 1277.5
A16: Inventories | C16: 1603.9 | D16: 2176.6 | E16: 1806.4 | F16: 1777.3 | G16: 2185.6
A17: Pre-paid Expenses and Other Current Assets | C17: 594.6 | D17: 483.7 | E17: 359.9 | F17: 313.1 | G17: 452.2
... A22: Current Portion of Long-Term Debt | C22: 998.9 | D22: 1749 | E22: 1818.6 | F22: 1248.9 | G22: 1498.9
A25: Sources: Starbucks Corporation 2025 Form 10-K. Starbucks Corporation 2022 Form 10-K. Starbucks Corporation 2023 Form 10-K. Historical financial data obtained from the company’s consolidated financial statements.

Sheet Historical Ratios
A1: Starbucks Corporation
A2: Historical Ratio Analysis
A3: Historical Period: 2021-2025
A5: Growth Ratios
A6: Ratio | C6: 2021 | D6: 2022 | E6: 2023 | F6: 2024 | G6: 2025
A7: Revenue Growth | C7: -- | D7: =('Historical Financials '!D7/'Historical Financials '!C7)-1 -> 0.10976029 | E7: =('Historical Financials '!E7/'Historical Financials '!D7)-1 -> 0.1155121 | F7: =('Historical Financials '!F7/'Historical Financials '!E7)-1 -> 0.0055760015 | G7: =('Historical Financials '!G7/'Historical Financials '!F7)-1 -> 0.027869152
A9: Profitability Ratios
A10: Ratio | C10: 2021 | D10: 2022 | E10: 2023 | F10: 2024 | G10: 2025
A11: Operating Margin | C11: =('Historical Financials '!C8/'Historical Financials '!C7) -> 0.16765311 | D11: =('Historical Financials '!D8/'Historical Financials '!D7) -> 0.14318626 | E11: =('Historical Financials '!E8/'Historical Financials '!E7) -> 0.16318838 | F11: =('Historical Financials '!F8/'Historical Financials '!F7) -> 0.14951266 | G11: =('Historical Financials '!G8/'Historical Financials '!G7) -> 0.078973978
A12: Effective Tax Rate | C12: =('Historical Financials '!C10/'Historical Financials '!C9) -> 0.21590845 | D12: =('Historical Financials '!D10/'Historical Financials '!D9) -> 0.224131 | E12: =('Historical Financials '!E10/'Historical Financials '!E9) -> 0.23643533 | F12: =('Historical Financials '!F10/'Historical Financials '!F9) -> 0.24293706 | G12: =('Historical Financials '!G10/'Historical Financials '!G9) -> 0.25948231
A14: Investment Ratios
A15: Ratio | C15: 2021 | D15: 2022 | E15: 2023 | F15: 2024 | G15: 2025
A16: D&A % Revenue | C16: =('Historical Financials '!C12/'Historical Financials '!C7) -> 0.052445579 | D16: =('Historical Financials '!D12/'Historical Financials '!D7) -> 0.047422815 | E16: =('Historical Financials '!E12/'Historical Financials '!E7) -> 0.040313435 | F16: =('Historical Financials '!F12/'Historical Financials '!F7) -> 0.04401789 | G16: =('Historical Financials '!G12/'Historical Financials '!G7) -> 0.047640946
A17: CapEx % Revenue | C17: ='Historical Financials '!C13/'Historical Financials '!C7 -> 0.050583952 | D17: ='Historical Financials '!D13/'Historical Financials '!D7 -> 0.057094043 | E17: ='Historical Financials '!E13/'Historical Financials '!E7 -> 0.064866187 | F17: ='Historical Financials '!F13/'Historical Financials '!F7 -> 0.076776997 | G17: ='Historical Financials '!G13/'Historical Financials '!G7 -> 0.062001807
A19: Working Capital ($ in millions)
A20: Ratio | C20: 2021 | D20: 2022 | E20: 2023 | F20: 2024 | G20: 2025
A21: Operating Assets | C21: =('Historical Financials '!C15+'Historical Financials '!C16+'Historical Financials '!C17) -> 3138.5 | D21: =('Historical Financials '!D15+'Historical Financials '!D16+'Historical Financials '!D17) -> 3835.8 | E21: =('Historical Financials '!E15+'Historical Financials '!E16+'Historical Financials '!E17) -> 3350.4 | F21: =('Historical Financials '!F15+'Historical Financials '!F16+'Historical Financials '!F17) -> 3304.2 | G21: =('Historical Financials '!G15+'Historical Financials '!G16+'Historical Financials '!G17) -> 3915.3
A22: Operating Liabilities | C22: =('Historical Financials '!C18+'Historical Financials '!C19+'Historical Financials '!C20) -> 3957.1 | D22: =('Historical Financials '!D18+'Historical Financials '!D19+'Historical Financials '!D20) -> 4340.2 | E22: =('Historical Financials '!E18+'Historical Financials '!E19+'Historical Financials '!E20) -> 4517.7 | F22: =('Historical Financials '!F18+'Historical Financials '!F19+'Historical Financials '!F20) -> 4576.8 | G22: =('Historical Financials '!G18+'Historical Financials '!G19+'Historical Financials '!G20) -> 5306.4
A23: Net Working Capital | C23: =C21-C22 -> -818.6 | D23: =D21-D22 -> -504.4 | E23: =E21-E22 -> -1167.3 | F23: =F21-F22 -> -1272.6 | G23: =G21-G22 -> -1391.1
A24: Change in Net Working Capital(NWC) | C24: -- | D24: =-504.4-(-818.6) -> 314.2 | E24: =E23-D23 -> -662.9 | F24: =F23-E23 -> -105.3 | G24: =G23-F23 -> -118.5

Sheet Assumptions 
A1: Starbucks Corporation
A2: Forecast Assumptions
A3: Forecast Period: 2026-2030
A5: Assumption | B5: Value | C5: Rationale
A6: Revenue Growth 2026 | B6: 0.05 | C6: Assumes revenue recovery after the 2024-2025 time period followed by gradual normalization.
A7: Revenue Growth 2027 | B7: 0.045 | C7: Reflects continued growth while beginning to moderate toward a mature long-term rate.
A8: Revenue Growth 2028 | B8: 0.04 | C8: Assumes continued normalization as the company progresses through the forecast period.
A9: Revenue Growth 2029 | B9: 0.035 | C9: Reflects slower growth as the company approaches a mature long-term growth rate.
A10: Revenue Growth 2030 | B10: 0.03 | C10: Represents normalized growth near the end of the explicit forecast period.
A11: Operating Margin | B11: 0.145 | C11: Based on historical operating margins and assumes stabilization following recent margin pressure.
A12: Effective Tax Rate | B12: 0.24 | C12: Based on the company’s historical effective tax rate range.
A13: D&A % Revenue | B13: 0.045 | C13: Based on historical depreciation and amortization as a percentage of revenue.
A14: CapEx % Revenue | B14: 0.06 | C14: Based on historical capital expenditures relative to revenue.
A15: Net Working Capital % Revenue | B15: -0.035 | C15: Based on historical net working capital levels relative to revenue.
A16: WACC | B16: 0.08 | C16: Assumed discount rate used to reflect the risk and required return of forecasted free cash flows.
A17: Terminal Growth Rate | B17: 0.025 | C17: Assumes a sustainable long-term growth rate beyond the five-year forecast period for a well established company

Sheet Forecast
A1: Starbucks Corporation
A2: Financial Forecast
A3: ($ in millions except percentages)
A5: Forecast | C5: 2026 | D5: 2027 | E5: 2028 | F5: 2029 | G5: 2030
A6: Revenue Growth | C6: ='Assumptions '!B6 -> 0.05 | D6: ='Assumptions '!B7 -> 0.045 | E6: ='Assumptions '!B8 -> 0.04 | F6: ='Assumptions '!B9 -> 0.035 | G6: ='Assumptions '!B10 -> 0.03
A7: Revenue | C7: ='Historical Financials '!G7*(1+C6) -> 39043.62 | D7: =C7*(1+D6) -> 40800.583 | E7: =D7*(1+E6) -> 42432.606 | F7: =E7*(1+F6) -> 43917.747 | G7: =F7*(1+G6) -> 45235.28
A8: Operating Margin | C8: ='Assumptions '!B11 -> 0.145 | D8: ='Assumptions '!B11 -> 0.145 | E8: ='Assumptions '!B11 -> 0.145 | F8: ='Assumptions '!B11 -> 0.145 | G8: ='Assumptions '!B11 -> 0.145
A9: EBIT | C9: =C7*C8 -> 5661.3249 | D9: =D7*D8 -> 5916.0845 | E9: =E7*E8 -> 6152.7279 | F9: =F7*F8 -> 6368.0734 | G9: =G7*G8 -> 6559.1156
A10: Taxes | C10: =C9*'Assumptions '!B12 -> 1358.718 | D10: =D9*'Assumptions '!B12 -> 1419.8603 | E10: =E9*'Assumptions '!B12 -> 1476.6547 | F10: =F9*'Assumptions '!B12 -> 1528.3376 | G10: =G9*'Assumptions '!B12 -> 1574.1877
A11: Net Operating Profit After Taxes(NOPAT) | C11: =C9-C10 -> 4302.6069 | D11: =D9-D10 -> 4496.2242 | E11: =E9-E10 -> 4676.0732 | F11: =F9-F10 -> 4839.7358 | G11: =G9-G10 -> 4984.9278
A12: D&A | C12: =C7*'Assumptions '!B13 -> 1756.9629 | D12: =D7*'Assumptions '!B13 -> 1836.0262 | E12: =E7*'Assumptions '!B13 -> 1909.4673 | F12: =F7*'Assumptions '!B13 -> 1976.2986 | G12: =G7*'Assumptions '!B13 -> 2035.5876
A13: CapEx | C13: =C7*'Assumptions '!B14 -> 2342.6172 | D13: =D7*'Assumptions '!B14 -> 2448.035 | E13: =E7*'Assumptions '!B14 -> 2545.9564 | F13: =F7*'Assumptions '!B14 -> 2635.0648 | G13: =G7*'Assumptions '!B14 -> 2714.1168
A14: Net Working Capital | C14: =C7*'Assumptions '!B15 -> -1366.5267 | D14: =D7*'Assumptions '!B15 -> -1428.0204 | E14: =E7*'Assumptions '!B15 -> -1485.1412 | F14: =F7*'Assumptions '!B15 -> -1537.1212 | G14: =G7*'Assumptions '!B15 -> -1583.2348
A15: Change in NWC | C15: =C14-'Historical Ratios'!G23 -> 24.5733 | D15: =Forecast!D14-Forecast!C14 -> -61.493702 | E15: =E14-D14 -> -57.120816 | F15: =F14-E14 -> -51.979943 | G15: =G14-F14 -> -46.113635
A16: Free Cash Flow | C16: =C11+C12-C13-C15 -> 3692.3793 | D16: =D11+D12-D13-D15 -> 3945.7092 | E16: =E11+E12-E13-E15 -> 4096.7049 | F16: =F11+F12-F13-F15 -> 4232.9495 | G16: =G11+G12-G13-G15 -> 4352.5123

Sheet DCF Valuation 
A1: Starbucks Corporation
A2: Discounted Cash Flow Valuation
A3: ($ in millions except Intrinsic Value per Share) | J3: Valuation Summary
J4: Based on the assumptions used on the Starbucks Corporation 5-year DCF model, there is an estimated Instrinsic Value per Share of $51.31.
A5: DCF Valuation ($ in millions except Intrinsic Value per Share) | B5: 2026 | C5: 2027 | D5: 2028 | E5: 2029 | F5: 2030 | G5: 2031
A6: Free Cash Flow | B6: =Forecast!C16 -> 3692.3793 | C6: =Forecast!D16 -> 3945.7092 | D6: =Forecast!E16 -> 4096.7049 | E6: =Forecast!F16 -> 4232.9495 | F6: =Forecast!G16 -> 4352.5123 | G6: =F6*(1+'Assumptions '!B17) -> 4461.3251
A7: Discount Factor | B7: =1/(1+'Assumptions '!B16)^1 -> 0.92592593 | C7: =1/(1+'Assumptions '!B16)^2 -> 0.85733882 | D7: =1/(1+'Assumptions '!B16)^3 -> 0.79383224 | E7: =1/(1+'Assumptions '!B16)^4 -> 0.73502985 | F7: =1/(1+'Assumptions '!B16)^5 -> 0.6805832
A8: Present Value of FCF | B8: =B6*B7 -> 3418.8697 | C8: =C6*C7 -> 3382.8097 | D8: =D6*D7 -> 3252.0965 | E8: =E6*E7 -> 3111.3442 | F8: =F6*F7 -> 2962.2467
A9: Terminal Value | B9: -- | C9: -- | D9: -- | E9: -- | F9: =G6/('Assumptions '!B16-'Assumptions '!B17) -> 81115.002
A10: Present Value of Terminal Value | B10: -- | C10: -- | D10: -- | E10: -- | F10: =F9*F7 -> 55205.507
A13: Enterprise Value | B13: =B8+C8+D8+E8+F8+F10 -> 71332.874
A14: Net Debt | B14: ='Historical Financials '!G21+'Historical Financials '!G22-'Historical Financials '!G14 -> 12855
A15: Equity Value | B15: =B13-B14 -> 58477.874
A16: Diluted Shares Outstanding | B16: 1139.8
A17: Intrinsic Value per Share | B17: =B15/B16 -> 51.305382

Sheet Sensitivity Analysis
A1: Starbucks Corporation
A2: DCF Sensitivity Analysis
A3: Intrinsic Value Per Share
A5: ='DCF Valuation '!B17 -> 51.305382
A6: WACC/Terminal Growth | B6: 0.02 | C6: 0.025 | D6: 0.03
A7: 0.075 | B7: 52.39 | C7: 57.59 | D7: 63.95
A8: 0.08 | B8: 47.05 | C8: 51.31 | D8: 56.41
A9: 0.085 | B9: 42.53 | C9: 46.07 | D9: 50.24
